{"nodes": [{"id": "d_vue_book_coffee_shop_implementation_guide_md", "label": "IMPLEMENTATION_GUIDE.md", "file_type": "document", "source_file": "IMPLEMENTATION_GUIDE.md", "source_location": "L1"}, {"id": "book_coffee_shop_implementation_guide_gu\u00eda_de_implementaci\u00f3n_paulus_paulu", "label": "Gu\u00eda de Implementaci\u00f3n \u2014 Paulus + Paulu", "file_type": "document", "source_file": "IMPLEMENTATION_GUIDE.md", "source_location": "L1"}, {"id": "book_coffee_shop_implementation_guide_1_resumen_del_proyecto_el_ascenso_de_muad_dib", "label": "1. Resumen del proyecto \u2014 *El ascenso de Muad'Dib*", "file_type": "document", "source_file": "IMPLEMENTATION_GUIDE.md", "source_location": "L10"}, {"id": "book_coffee_shop_implementation_guide_2_frontend_paulus_vue_3_rostro_de_paul_ante_los_fremen", "label": "2. Frontend \u2014 Paulus (Vue 3) \u2014 *Rostro de Paul ante los fremen*", "file_type": "document", "source_file": "IMPLEMENTATION_GUIDE.md", "source_location": "L22"}, {"id": "book_coffee_shop_implementation_guide_2_1_arquitectura_caladan_estructura_noble_en_cuatro_capas", "label": "2.1 Arquitectura \u2014 *Caladan: estructura noble en cuatro capas*", "file_type": "document", "source_file": "IMPLEMENTATION_GUIDE.md", "source_location": "L24"}, {"id": "book_coffee_shop_implementation_guide_2_2_patr\u00f3n_de_inyecci\u00f3n_de_dependencias_mentat_thufir", "label": "2.2 Patr\u00f3n de inyecci\u00f3n de dependencias \u2014 *Mentat Thufir*", "file_type": "document", "source_file": "IMPLEMENTATION_GUIDE.md", "source_location": "L37"}, {"id": "book_coffee_shop_implementation_guide_2_3_servicios_http_capa_application_exploradores_fremen", "label": "2.3 Servicios HTTP (capa application) \u2014 *Exploradores fremen*", "file_type": "document", "source_file": "IMPLEMENTATION_GUIDE.md", "source_location": "L51"}, {"id": "book_coffee_shop_implementation_guide_2_4_stores_pinia_sietch_tabr_memoria_colectiva", "label": "2.4 Stores (Pinia) \u2014 *Sietch Tabr: memoria colectiva*", "file_type": "document", "source_file": "IMPLEMENTATION_GUIDE.md", "source_location": "L69"}, {"id": "book_coffee_shop_implementation_guide_2_5_composables_weirding_way", "label": "2.5 Composables \u2014 *Weirding Way*", "file_type": "document", "source_file": "IMPLEMENTATION_GUIDE.md", "source_location": "L82"}, {"id": "book_coffee_shop_implementation_guide_2_6_enrutamiento_navegadores_guild", "label": "2.6 Enrutamiento \u2014 *Navegadores Guild*", "file_type": "document", "source_file": "IMPLEMENTATION_GUIDE.md", "source_location": "L88"}, {"id": "book_coffee_shop_implementation_guide_2_7_componentes_principales_arsenal_del_sietch", "label": "2.7 Componentes principales \u2014 *Arsenal del sietch*", "file_type": "document", "source_file": "IMPLEMENTATION_GUIDE.md", "source_location": "L94"}, {"id": "book_coffee_shop_implementation_guide_2_8_manejo_de_errores_voz_bene_gesserit", "label": "2.8 Manejo de errores \u2014 *Voz Bene Gesserit*", "file_type": "document", "source_file": "IMPLEMENTATION_GUIDE.md", "source_location": "L124"}, {"id": "book_coffee_shop_implementation_guide_2_9_autenticaci\u00f3n_sello_atreides", "label": "2.9 Autenticaci\u00f3n \u2014 *Sello Atreides*", "file_type": "document", "source_file": "IMPLEMENTATION_GUIDE.md", "source_location": "L131"}, {"id": "book_coffee_shop_implementation_guide_3_backend_paulu_go_api_sardaukar_disciplina_del_desierto", "label": "3. Backend \u2014 Paulu (Go API) \u2014 *Sardaukar: disciplina del desierto*", "file_type": "document", "source_file": "IMPLEMENTATION_GUIDE.md", "source_location": "L140"}, {"id": "book_coffee_shop_implementation_guide_3_1_arquitectura", "label": "3.1 Arquitectura", "file_type": "document", "source_file": "IMPLEMENTATION_GUIDE.md", "source_location": "L142"}, {"id": "book_coffee_shop_implementation_guide_3_2_productos_modelo_de_dominio", "label": "3.2 Productos \u2014 Modelo de dominio", "file_type": "document", "source_file": "IMPLEMENTATION_GUIDE.md", "source_location": "L158"}, {"id": "book_coffee_shop_implementation_guide_3_3_productos_use_case", "label": "3.3 Productos \u2014 Use case", "file_type": "document", "source_file": "IMPLEMENTATION_GUIDE.md", "source_location": "L174"}, {"id": "book_coffee_shop_implementation_guide_3_4_productos_handler_http", "label": "3.4 Productos \u2014 Handler HTTP", "file_type": "document", "source_file": "IMPLEMENTATION_GUIDE.md", "source_location": "L199"}, {"id": "book_coffee_shop_implementation_guide_3_5_productos_base_de_datos", "label": "3.5 Productos \u2014 Base de datos", "file_type": "document", "source_file": "IMPLEMENTATION_GUIDE.md", "source_location": "L209"}, {"id": "book_coffee_shop_implementation_guide_3_6_helpers_compartidos", "label": "3.6 Helpers compartidos", "file_type": "document", "source_file": "IMPLEMENTATION_GUIDE.md", "source_location": "L226"}, {"id": "book_coffee_shop_implementation_guide_3_7_configuraci\u00f3n", "label": "3.7 Configuraci\u00f3n", "file_type": "document", "source_file": "IMPLEMENTATION_GUIDE.md", "source_location": "L234"}, {"id": "book_coffee_shop_implementation_guide_4_registro_de_productos_flujo_completo", "label": "4. Registro de productos \u2014 Flujo completo", "file_type": "document", "source_file": "IMPLEMENTATION_GUIDE.md", "source_location": "L245"}, {"id": "book_coffee_shop_implementation_guide_4_1_frontend_backend", "label": "4.1 Frontend \u2192 Backend", "file_type": "document", "source_file": "IMPLEMENTATION_GUIDE.md", "source_location": "L247"}, {"id": "book_coffee_shop_implementation_guide_4_2_consideraciones_de_dise\u00f1o", "label": "4.2 Consideraciones de dise\u00f1o", "file_type": "document", "source_file": "IMPLEMENTATION_GUIDE.md", "source_location": "L271"}, {"id": "book_coffee_shop_implementation_guide_5_graphify_an\u00e1lisis_de_grafos_de_c\u00f3digo_mentat_thufir", "label": "5. Graphify \u2014 An\u00e1lisis de grafos de c\u00f3digo \u2014 *Mentat Thufir*", "file_type": "document", "source_file": "IMPLEMENTATION_GUIDE.md", "source_location": "L280"}, {"id": "book_coffee_shop_implementation_guide_5_1_herramienta", "label": "5.1 Herramienta", "file_type": "document", "source_file": "IMPLEMENTATION_GUIDE.md", "source_location": "L282"}, {"id": "book_coffee_shop_implementation_guide_5_2_resultados", "label": "5.2 Resultados", "file_type": "document", "source_file": "IMPLEMENTATION_GUIDE.md", "source_location": "L291"}, {"id": "book_coffee_shop_implementation_guide_5_3_archivos_generados", "label": "5.3 Archivos generados", "file_type": "document", "source_file": "IMPLEMENTATION_GUIDE.md", "source_location": "L298"}, {"id": "book_coffee_shop_implementation_guide_5_4_skills_de_opencode", "label": "5.4 Skills de OpenCode", "file_type": "document", "source_file": "IMPLEMENTATION_GUIDE.md", "source_location": "L307"}, {"id": "book_coffee_shop_implementation_guide_6_nuevo_proyecto_generado_paulu_vue", "label": "6. Nuevo proyecto generado \u2014 Paulu (Vue)", "file_type": "document", "source_file": "IMPLEMENTATION_GUIDE.md", "source_location": "L321"}, {"id": "book_coffee_shop_implementation_guide_7_convenciones_del_c\u00f3digo_c\u00f3digo_de_honor_atreides", "label": "7. Convenciones del c\u00f3digo \u2014 *C\u00f3digo de honor Atreides*", "file_type": "document", "source_file": "IMPLEMENTATION_GUIDE.md", "source_location": "L331"}, {"id": "book_coffee_shop_implementation_guide_7_1_frontend_lenguaje_de_usul", "label": "7.1 Frontend \u2014 *Lenguaje de Usul*", "file_type": "document", "source_file": "IMPLEMENTATION_GUIDE.md", "source_location": "L333"}, {"id": "book_coffee_shop_implementation_guide_7_2_backend_lenguaje_del_imperio", "label": "7.2 Backend \u2014 *Lenguaje del Imperio*", "file_type": "document", "source_file": "IMPLEMENTATION_GUIDE.md", "source_location": "L344"}, {"id": "book_coffee_shop_implementation_guide_8_variables_de_entorno_coordenadas_del_guild_navigator", "label": "8. Variables de entorno \u2014 *Coordenadas del Guild Navigator*", "file_type": "document", "source_file": "IMPLEMENTATION_GUIDE.md", "source_location": "L354"}, {"id": "book_coffee_shop_implementation_guide_9_comandos_\u00fatiles_manual_del_ornit\u00f3ptero", "label": "9. Comandos \u00fatiles \u2014 *Manual del ornit\u00f3ptero*", "file_type": "document", "source_file": "IMPLEMENTATION_GUIDE.md", "source_location": "L364"}, {"id": "book_coffee_shop_implementation_guide_frontend_paulus", "label": "Frontend (Paulus)", "file_type": "document", "source_file": "IMPLEMENTATION_GUIDE.md", "source_location": "L366"}, {"id": "book_coffee_shop_implementation_guide_backend_paulu", "label": "Backend (Paulu)", "file_type": "document", "source_file": "IMPLEMENTATION_GUIDE.md", "source_location": "L384"}, {"id": "book_coffee_shop_implementation_guide_10_referencias", "label": "10. Referencias", "file_type": "document", "source_file": "IMPLEMENTATION_GUIDE.md", "source_location": "L401"}], "edges": [{"source": "d_vue_book_coffee_shop_implementation_guide_md", "target": "book_coffee_shop_implementation_guide_gu\u00eda_de_implementaci\u00f3n_paulus_paulu", "relation": "contains", "confidence": "EXTRACTED", "source_file": "IMPLEMENTATION_GUIDE.md", "source_location": "L1", "weight": 1.0}, {"source": "book_coffee_shop_implementation_guide_gu\u00eda_de_implementaci\u00f3n_paulus_paulu", "target": "book_coffee_shop_implementation_guide_1_resumen_del_proyecto_el_ascenso_de_muad_dib", "relation": "contains", "confidence": "EXTRACTED", "source_file": "IMPLEMENTATION_GUIDE.md", "source_location": "L10", "weight": 1.0}, {"source": "book_coffee_shop_implementation_guide_gu\u00eda_de_implementaci\u00f3n_paulus_paulu", "target": "book_coffee_shop_implementation_guide_2_frontend_paulus_vue_3_rostro_de_paul_ante_los_fremen", "relation": "contains", "confidence": "EXTRACTED", "source_file": "IMPLEMENTATION_GUIDE.md", "source_location": "L22", "weight": 1.0}, {"source": "book_coffee_shop_implementation_guide_2_frontend_paulus_vue_3_rostro_de_paul_ante_los_fremen", "target": "book_coffee_shop_implementation_guide_2_1_arquitectura_caladan_estructura_noble_en_cuatro_capas", "relation": "contains", "confidence": "EXTRACTED", "source_file": "IMPLEMENTATION_GUIDE.md", "source_location": "L24", "weight": 1.0}, {"source": "book_coffee_shop_implementation_guide_2_frontend_paulus_vue_3_rostro_de_paul_ante_los_fremen", "target": "book_coffee_shop_implementation_guide_2_2_patr\u00f3n_de_inyecci\u00f3n_de_dependencias_mentat_thufir", "relation": "contains", "confidence": "EXTRACTED", "source_file": "IMPLEMENTATION_GUIDE.md", "source_location": "L37", "weight": 1.0}, {"source": "book_coffee_shop_implementation_guide_2_frontend_paulus_vue_3_rostro_de_paul_ante_los_fremen", "target": "book_coffee_shop_implementation_guide_2_3_servicios_http_capa_application_exploradores_fremen", "relation": "contains", "confidence": "EXTRACTED", "source_file": "IMPLEMENTATION_GUIDE.md", "source_location": "L51", "weight": 1.0}, {"source": "book_coffee_shop_implementation_guide_2_frontend_paulus_vue_3_rostro_de_paul_ante_los_fremen", "target": "book_coffee_shop_implementation_guide_2_4_stores_pinia_sietch_tabr_memoria_colectiva", "relation": "contains", "confidence": "EXTRACTED", "source_file": "IMPLEMENTATION_GUIDE.md", "source_location": "L69", "weight": 1.0}, {"source": "book_coffee_shop_implementation_guide_2_frontend_paulus_vue_3_rostro_de_paul_ante_los_fremen", "target": "book_coffee_shop_implementation_guide_2_5_composables_weirding_way", "relation": "contains", "confidence": "EXTRACTED", "source_file": "IMPLEMENTATION_GUIDE.md", "source_location": "L82", "weight": 1.0}, {"source": "book_coffee_shop_implementation_guide_2_frontend_paulus_vue_3_rostro_de_paul_ante_los_fremen", "target": "book_coffee_shop_implementation_guide_2_6_enrutamiento_navegadores_guild", "relation": "contains", "confidence": "EXTRACTED", "source_file": "IMPLEMENTATION_GUIDE.md", "source_location": "L88", "weight": 1.0}, {"source": "book_coffee_shop_implementation_guide_2_frontend_paulus_vue_3_rostro_de_paul_ante_los_fremen", "target": "book_coffee_shop_implementation_guide_2_7_componentes_principales_arsenal_del_sietch", "relation": "contains", "confidence": "EXTRACTED", "source_file": "IMPLEMENTATION_GUIDE.md", "source_location": "L94", "weight": 1.0}, {"source": "book_coffee_shop_implementation_guide_2_frontend_paulus_vue_3_rostro_de_paul_ante_los_fremen", "target": "book_coffee_shop_implementation_guide_2_8_manejo_de_errores_voz_bene_gesserit", "relation": "contains", "confidence": "EXTRACTED", "source_file": "IMPLEMENTATION_GUIDE.md", "source_location": "L124", "weight": 1.0}, {"source": "book_coffee_shop_implementation_guide_2_frontend_paulus_vue_3_rostro_de_paul_ante_los_fremen", "target": "book_coffee_shop_implementation_guide_2_9_autenticaci\u00f3n_sello_atreides", "relation": "contains", "confidence": "EXTRACTED", "source_file": "IMPLEMENTATION_GUIDE.md", "source_location": "L131", "weight": 1.0}, {"source": "book_coffee_shop_implementation_guide_gu\u00eda_de_implementaci\u00f3n_paulus_paulu", "target": "book_coffee_shop_implementation_guide_3_backend_paulu_go_api_sardaukar_disciplina_del_desierto", "relation": "contains", "confidence": "EXTRACTED", "source_file": "IMPLEMENTATION_GUIDE.md", "source_location": "L140", "weight": 1.0}, {"source": "book_coffee_shop_implementation_guide_3_backend_paulu_go_api_sardaukar_disciplina_del_desierto", "target": "book_coffee_shop_implementation_guide_3_1_arquitectura", "relation": "contains", "confidence": "EXTRACTED", "source_file": "IMPLEMENTATION_GUIDE.md", "source_location": "L142", "weight": 1.0}, {"source": "book_coffee_shop_implementation_guide_3_backend_paulu_go_api_sardaukar_disciplina_del_desierto", "target": "book_coffee_shop_implementation_guide_3_2_productos_modelo_de_dominio", "relation": "contains", "confidence": "EXTRACTED", "source_file": "IMPLEMENTATION_GUIDE.md", "source_location": "L158", "weight": 1.0}, {"source": "book_coffee_shop_implementation_guide_3_backend_paulu_go_api_sardaukar_disciplina_del_desierto", "target": "book_coffee_shop_implementation_guide_3_3_productos_use_case", "relation": "contains", "confidence": "EXTRACTED", "source_file": "IMPLEMENTATION_GUIDE.md", "source_location": "L174", "weight": 1.0}, {"source": "book_coffee_shop_implementation_guide_3_backend_paulu_go_api_sardaukar_disciplina_del_desierto", "target": "book_coffee_shop_implementation_guide_3_4_productos_handler_http", "relation": "contains", "confidence": "EXTRACTED", "source_file": "IMPLEMENTATION_GUIDE.md", "source_location": "L199", "weight": 1.0}, {"source": "book_coffee_shop_implementation_guide_3_backend_paulu_go_api_sardaukar_disciplina_del_desierto", "target": "book_coffee_shop_implementation_guide_3_5_productos_base_de_datos", "relation": "contains", "confidence": "EXTRACTED", "source_file": "IMPLEMENTATION_GUIDE.md", "source_location": "L209", "weight": 1.0}, {"source": "book_coffee_shop_implementation_guide_3_backend_paulu_go_api_sardaukar_disciplina_del_desierto", "target": "book_coffee_shop_implementation_guide_3_6_helpers_compartidos", "relation": "contains", "confidence": "EXTRACTED", "source_file": "IMPLEMENTATION_GUIDE.md", "source_location": "L226", "weight": 1.0}, {"source": "book_coffee_shop_implementation_guide_3_backend_paulu_go_api_sardaukar_disciplina_del_desierto", "target": "book_coffee_shop_implementation_guide_3_7_configuraci\u00f3n", "relation": "contains", "confidence": "EXTRACTED", "source_file": "IMPLEMENTATION_GUIDE.md", "source_location": "L234", "weight": 1.0}, {"source": "book_coffee_shop_implementation_guide_gu\u00eda_de_implementaci\u00f3n_paulus_paulu", "target": "book_coffee_shop_implementation_guide_4_registro_de_productos_flujo_completo", "relation": "contains", "confidence": "EXTRACTED", "source_file": "IMPLEMENTATION_GUIDE.md", "source_location": "L245", "weight": 1.0}, {"source": "book_coffee_shop_implementation_guide_4_registro_de_productos_flujo_completo", "target": "book_coffee_shop_implementation_guide_4_1_frontend_backend", "relation": "contains", "confidence": "EXTRACTED", "source_file": "IMPLEMENTATION_GUIDE.md", "source_location": "L247", "weight": 1.0}, {"source": "book_coffee_shop_implementation_guide_4_registro_de_productos_flujo_completo", "target": "book_coffee_shop_implementation_guide_4_2_consideraciones_de_dise\u00f1o", "relation": "contains", "confidence": "EXTRACTED", "source_file": "IMPLEMENTATION_GUIDE.md", "source_location": "L271", "weight": 1.0}, {"source": "book_coffee_shop_implementation_guide_gu\u00eda_de_implementaci\u00f3n_paulus_paulu", "target": "book_coffee_shop_implementation_guide_5_graphify_an\u00e1lisis_de_grafos_de_c\u00f3digo_mentat_thufir", "relation": "contains", "confidence": "EXTRACTED", "source_file": "IMPLEMENTATION_GUIDE.md", "source_location": "L280", "weight": 1.0}, {"source": "book_coffee_shop_implementation_guide_5_graphify_an\u00e1lisis_de_grafos_de_c\u00f3digo_mentat_thufir", "target": "book_coffee_shop_implementation_guide_5_1_herramienta", "relation": "contains", "confidence": "EXTRACTED", "source_file": "IMPLEMENTATION_GUIDE.md", "source_location": "L282", "weight": 1.0}, {"source": "book_coffee_shop_implementation_guide_5_graphify_an\u00e1lisis_de_grafos_de_c\u00f3digo_mentat_thufir", "target": "book_coffee_shop_implementation_guide_5_2_resultados", "relation": "contains", "confidence": "EXTRACTED", "source_file": "IMPLEMENTATION_GUIDE.md", "source_location": "L291", "weight": 1.0}, {"source": "book_coffee_shop_implementation_guide_5_graphify_an\u00e1lisis_de_grafos_de_c\u00f3digo_mentat_thufir", "target": "book_coffee_shop_implementation_guide_5_3_archivos_generados", "relation": "contains", "confidence": "EXTRACTED", "source_file": "IMPLEMENTATION_GUIDE.md", "source_location": "L298", "weight": 1.0}, {"source": "book_coffee_shop_implementation_guide_5_graphify_an\u00e1lisis_de_grafos_de_c\u00f3digo_mentat_thufir", "target": "book_coffee_shop_implementation_guide_5_4_skills_de_opencode", "relation": "contains", "confidence": "EXTRACTED", "source_file": "IMPLEMENTATION_GUIDE.md", "source_location": "L307", "weight": 1.0}, {"source": "book_coffee_shop_implementation_guide_gu\u00eda_de_implementaci\u00f3n_paulus_paulu", "target": "book_coffee_shop_implementation_guide_6_nuevo_proyecto_generado_paulu_vue", "relation": "contains", "confidence": "EXTRACTED", "source_file": "IMPLEMENTATION_GUIDE.md", "source_location": "L321", "weight": 1.0}, {"source": "book_coffee_shop_implementation_guide_gu\u00eda_de_implementaci\u00f3n_paulus_paulu", "target": "book_coffee_shop_implementation_guide_7_convenciones_del_c\u00f3digo_c\u00f3digo_de_honor_atreides", "relation": "contains", "confidence": "EXTRACTED", "source_file": "IMPLEMENTATION_GUIDE.md", "source_location": "L331", "weight": 1.0}, {"source": "book_coffee_shop_implementation_guide_7_convenciones_del_c\u00f3digo_c\u00f3digo_de_honor_atreides", "target": "book_coffee_shop_implementation_guide_7_1_frontend_lenguaje_de_usul", "relation": "contains", "confidence": "EXTRACTED", "source_file": "IMPLEMENTATION_GUIDE.md", "source_location": "L333", "weight": 1.0}, {"source": "book_coffee_shop_implementation_guide_7_convenciones_del_c\u00f3digo_c\u00f3digo_de_honor_atreides", "target": "book_coffee_shop_implementation_guide_7_2_backend_lenguaje_del_imperio", "relation": "contains", "confidence": "EXTRACTED", "source_file": "IMPLEMENTATION_GUIDE.md", "source_location": "L344", "weight": 1.0}, {"source": "book_coffee_shop_implementation_guide_gu\u00eda_de_implementaci\u00f3n_paulus_paulu", "target": "book_coffee_shop_implementation_guide_8_variables_de_entorno_coordenadas_del_guild_navigator", "relation": "contains", "confidence": "EXTRACTED", "source_file": "IMPLEMENTATION_GUIDE.md", "source_location": "L354", "weight": 1.0}, {"source": "book_coffee_shop_implementation_guide_gu\u00eda_de_implementaci\u00f3n_paulus_paulu", "target": "book_coffee_shop_implementation_guide_9_comandos_\u00fatiles_manual_del_ornit\u00f3ptero", "relation": "contains", "confidence": "EXTRACTED", "source_file": "IMPLEMENTATION_GUIDE.md", "source_location": "L364", "weight": 1.0}, {"source": "book_coffee_shop_implementation_guide_9_comandos_\u00fatiles_manual_del_ornit\u00f3ptero", "target": "book_coffee_shop_implementation_guide_frontend_paulus", "relation": "contains", "confidence": "EXTRACTED", "source_file": "IMPLEMENTATION_GUIDE.md", "source_location": "L366", "weight": 1.0}, {"source": "book_coffee_shop_implementation_guide_9_comandos_\u00fatiles_manual_del_ornit\u00f3ptero", "target": "book_coffee_shop_implementation_guide_backend_paulu", "relation": "contains", "confidence": "EXTRACTED", "source_file": "IMPLEMENTATION_GUIDE.md", "source_location": "L384", "weight": 1.0}, {"source": "book_coffee_shop_implementation_guide_gu\u00eda_de_implementaci\u00f3n_paulus_paulu", "target": "book_coffee_shop_implementation_guide_10_referencias", "relation": "contains", "confidence": "EXTRACTED", "source_file": "IMPLEMENTATION_GUIDE.md", "source_location": "L401", "weight": 1.0}], "input_tokens": 0, "output_tokens": 0}